superduper_redis/__init__.py
superduper_redis/data_backend.py
superduper_redis-0.10.0.dist-info/METADATA
superduper_redis-0.10.0.dist-info/WHEEL
superduper_redis-0.10.0.dist-info/top_level.txt
superduper_redis-0.10.0.dist-info/RECORD
