Metadata-Version: 2.4
Name: superduper_redis
Version: 0.10.0
Summary: superduper allows users to work with arbitrary sklearn estimators, with additional support for pre-, post-processing and input/ output data-types.
Maintainer-email: "superduper.io, Inc." <opensource@superduper.io>
Project-URL: homepage, https://superduper.io
Project-URL: documentation, https://docs.superduper.io/docs/intro
Project-URL: source, https://github.com/superduper-io/superduper
Keywords: databases,mongodb,data-science,machine-learning,mlops,vector-database,ai
Requires-Python: >=3.10
Requires-Dist: redis
Provides-Extra: test
